datasette_chartjs/__init__.py
datasette_chartjs/static/datasette-chartjs.js
datasette_chartjs-0.2.0.dist-info/METADATA
datasette_chartjs-0.2.0.dist-info/WHEEL
datasette_chartjs-0.2.0.dist-info/entry_points.txt
datasette_chartjs-0.2.0.dist-info/top_level.txt
datasette_chartjs-0.2.0.dist-info/RECORD
