Metadata-Version: 2.1
Name: datasette-chartjs
Version: 0.2.0
Summary: Chart.js integration for datasette
Home-page: https://github.com/MarkusH/datasette-chartjs
Author: Markus Holtermann
License: Apache License, Version 2.0
Project-URL: Issues, https://github.com/MarkusH/datasette-chartjs/issues
Project-URL: CI, https://github.com/MarkusH/datasette-chartjs/actions
Project-URL: Changelog, https://github.com/MarkusH/datasette-chartjs/blob/main/CHANGES.md
Platform: UNKNOWN
Requires-Python: >=3.6
Requires-Dist: datasette
Provides-Extra: dev
Requires-Dist: pre-commit ; extra == 'dev'
Provides-Extra: test
Requires-Dist: pytest ; extra == 'test'
Requires-Dist: pytest-asyncio ; extra == 'test'
